shopback_sdk/__init__.py
shopback_sdk/example.py
shopback_sdk-0.1.0.dist-info/LICENSE
shopback_sdk-0.1.0.dist-info/WHEEL
shopback_sdk-0.1.0.dist-info/METADATA
shopback_sdk-0.1.0.dist-info/RECORD
