Metadata-Version: 2.1
Name: shopback-sdk
Version: 0.1.0
Summary: shopback.ru - no code shop constructor and cafe for telegram
Home-page: https://github.com/ktsstudio/shopback-sdk
License: MIT
Author: ktsstudio
Author-email: hello@ktsstudio.com
Requires-Python: >=3.9,<4.0
Classifier: Development Status :: 3 - Alpha
Classifier: Intended Audience :: Developers
Classifier: License :: OSI Approved :: MIT License
Classifier: Operating System :: OS Independent
Classifier: Programming Language :: Python :: 3
Classifier: Programming Language :: Python :: 3.9
Classifier: Programming Language :: Python :: 3.10
Classifier: Programming Language :: Python :: 3.11
Classifier: Programming Language :: Python :: 3
Classifier: Programming Language :: Python :: 3.9
Classifier: Topic :: Software Development :: Libraries :: Python Modules
Project-URL: Repository, https://github.com/ktsstudio/shopback-sdk
